MANIFEST.in
README.txt
setup.py
Parterre.egg-info/PKG-INFO
Parterre.egg-info/SOURCES.txt
Parterre.egg-info/dependency_links.txt
Parterre.egg-info/entry_points.txt
Parterre.egg-info/requires.txt
Parterre.egg-info/top_level.txt
Parterre.egg-info/zip-safe
parterre/__init__.py
parterre/datc.py
parterre/loader.py
parterre/testing.py
parterre/data/abstraction2.cfg
parterre/data/african2.cfg
parterre/data/americas4.cfg
parterre/data/chromatic.cfg
parterre/data/classical.cfg
parterre/data/fleet_rome.cfg
parterre/data/hundred3.cfg
parterre/data/hundred31.cfg
parterre/data/hundred32.cfg
parterre/data/iberian2.cfg
parterre/data/modern.cfg
parterre/data/sailho.cfg
parterre/data/shift_around.cfg
parterre/data/south_america32.cfg
parterre/data/south_america51.cfg
parterre/data/south_east_asia3.cfg
parterre/data/versailles3.cfg
parterre/data/world3.cfg