Metadata-Version: 1.0
Name: Parterre
Version: 1.4.1
Summary: A set of variants for the Parlance Diplomacy Framework.
Home-page: UNKNOWN
Author: Eric Wald
Author-email: breadman@users.sourceforge.net
License: Non-commercial
Keywords: daide diplomacy board game variants
Platform: Any
Classifier: Development Status :: 4 - Beta
Classifier: Environment :: Console
Classifier: Environment :: Console :: Curses
Classifier: Environment :: No Input/Output (Daemon)
Classifier: License :: Free for non-commercial use
Classifier: Natural Language :: English
Classifier: Operating System :: OS Independent
Classifier: Programming Language :: Python
Classifier: Topic :: Games/Entertainment :: Board Games
Classifier: Topic :: Games/Entertainment :: Turn Based Strategy
